ninagram/__init__.py
ninagram/apps.py
ninagram/auth.py
ninagram/bot.py
ninagram/cache.py
ninagram/handlers.py
ninagram/middlewares.py
ninagram/models.py
ninagram/response.py
ninagram/runtime.py
ninagram/state.py
ninagram/todo.py
ninagram/urls.py
ninagram/views.py
ninagram/exceptions/__init__.py
ninagram/fields/__init__.py
ninagram/fields/base.py
ninagram/fields/char.py
ninagram/fields/choice.py
ninagram/fields/datetiming.py
ninagram/fields/password.py
ninagram/inputs/__init__.py
ninagram/inputs/base.py
ninagram/inputs/char.py
ninagram/inputs/choice.py
ninagram/inputs/datetiming.py
ninagram/inputs/password.py
ninagram/migrations/0001_initial.py
ninagram/migrations/0002_auto_20190822_1727.py
ninagram/migrations/__init__.py
ninagram/states/__init__.py
ninagram/states/base.py
ninagram/states/forms.py
ninagram/states/models.py
ninagram/templatetags/__init__.py
ninagram/templatetags/models.py
ninagram/templatetags/tg_bot.py
ninagram/templatetags/actions/__init__.py
ninagram/templatetags/actions/sending.py
ninagram-0.1.4.dist-info/LICENSE.txt
ninagram-0.1.4.dist-info/METADATA
ninagram-0.1.4.dist-info/WHEEL
ninagram-0.1.4.dist-info/top_level.txt
ninagram-0.1.4.dist-info/RECORD
