Metadata-Version: 2.1
Name: ninagram
Version: 0.1.4
Summary: A framework on top of Django and Python-telegram-bot for building Telegram bots
Home-page: https://github.com/jefcolbi/ninagram
Author: jefcolbi
Author-email: jefcolbi@mboatek.com
License: MIT
Platform: UNKNOWN
Classifier: Natural Language :: English
Classifier: Natural Language :: French
Classifier: Development Status :: 5 - Production/Stable
Classifier: Programming Language :: Python
Classifier: Programming Language :: Python :: 3.6
Classifier: License :: OSI Approved :: GNU General Public License v3 or later (GPLv3+)
Requires-Python: >=3.6.0
Requires-Dist: django
Requires-Dist: python-telegram-bot
Requires-Dist: tzlocal
Requires-Dist: django-timezone-field
Requires-Dist: loguru
